pyloremgen/__init__.py
pyloremgen/data/__init__.py
pyloremgen/data/lorem_ipsum_wordlist.json
pyloremgen/generator/__init__.py
pyloremgen/generator/lorem_pdf.py
pyloremgen/generator/lorem_text.py
pyloremgen/generator/pdf_utils/__init__.py
pyloremgen/generator/pdf_utils/cover_page_template.py
pyloremgen/generator/pdf_utils/pdf_page_settings.py
pyloremgen/utilities/__init__.py
pyloremgen/utilities/file_helper.py
tests/__init__.py
tests/test_lorem_text.py
tests/test_utils.py
pyloremGen-2.0.0.dist-info/LICENSE
pyloremGen-2.0.0.dist-info/METADATA
pyloremGen-2.0.0.dist-info/WHEEL
pyloremGen-2.0.0.dist-info/top_level.txt
pyloremGen-2.0.0.dist-info/RECORD
