Metadata-Version: 2.1
Name: pyloremGen
Version: 2.0.0
Summary: A Python library for generating Lorem Ipsum text.
Home-page: https://github.com/oVitorio-ac/pyloremGen/
Author: Vitório Augusto Cavalheiro
License: MIT
Requires-Python: >=3.9.0, <4
License-File: LICENSE
